{
    "username": "tb_51fe3b02_0",
    "is_npc": true,
    "race": "Zhareen",
    "profession": "Emissary of Peace",
    "stance": "Diplomatic Negotiator",
    "vita": "As an esteemed Zhareen Emissary from the neutral planet Zeta-Quint, I have spent my life dedicated to maintaining harmony among conflicting galactic factions. My skills in negotin...",
    "portrait_prompt": "A dignified and composed Zhareen diplomat stands atop a transparent hovercraft throne with an air of authority; the glow from their bio-luminescent skin subtly highlights features, casting gentle light across my face as I gaze into viewers' eyes. The ambient backdrop is Zeta-Quint’s neutral zone flags fluttering in zero gravity.",
    "generated_at": "2026-04-10T06:24:13+00:00"
}